test_distributions_km/Binomialdistribution.py
test_distributions_km/Gaussiandistribution.py
test_distributions_km/Generaldistribution.py
test_distributions_km/__init__.py
test_distributions_km-1.0.dist-info/DESCRIPTION.rst
test_distributions_km-1.0.dist-info/METADATA
test_distributions_km-1.0.dist-info/RECORD
test_distributions_km-1.0.dist-info/WHEEL
test_distributions_km-1.0.dist-info/metadata.json
test_distributions_km-1.0.dist-info/top_level.txt
