Metadata-Version: 2.0
Name: test-distributions-km
Version: 1.0
Summary: Gaussian and Binomial distributions
Home-page: UNKNOWN
Author: Kengo Matsumura
Author-email: UNKNOWN
License: UNKNOWN
Platform: UNKNOWN
